scheduler/__init__.py
scheduler/client.py
scheduler/retry_client.py
worker/__init__.py
worker/call.py
worker/worker.py
go_server_sdk-2.0.1.dist-info/METADATA
go_server_sdk-2.0.1.dist-info/WHEEL
go_server_sdk-2.0.1.dist-info/top_level.txt
go_server_sdk-2.0.1.dist-info/RECORD
