Metadata-Version: 2.4
Name: go-server-sdk
Version: 2.0.1
Summary: Python SDK for go-server distributed task scheduling system
Home-page: https://github.com/go-enols/go-server
Author: go-server team
Author-email: 
Project-URL: Bug Reports, https://github.com/go-enols/go-server/issues
Project-URL: Source, https://github.com/go-enols/go-server
Project-URL: Documentation, https://github.com/go-enols/go-server/blob/main/README.md
Keywords: distributed computing,task scheduling,websocket,rpc
Classifier: Development Status :: 4 - Beta
Classifier: Intended Audience :: Developers
Classifier: License :: OSI Approved :: MIT License
Classifier: Operating System :: OS Independent
Classifier: Programming Language :: Python :: 3
Classifier: Programming Language :: Python :: 3.7
Classifier: Programming Language :: Python :: 3.8
Classifier: Programming Language :: Python :: 3.9
Classifier: Programming Language :: Python :: 3.10
Classifier: Programming Language :: Python :: 3.11
Classifier: Topic :: Software Development :: Libraries :: Python Modules
Classifier: Topic :: System :: Distributed Computing
Requires-Python: >=3.7
Requires-Dist: requests>=2.25.0
Requires-Dist: websocket-client>=1.0.0
Requires-Dist: typing-extensions>=3.7.4; python_version < "3.8"
Provides-Extra: dev
Requires-Dist: pytest>=6.0; extra == "dev"
Requires-Dist: pytest-asyncio>=0.18.0; extra == "dev"
Requires-Dist: black>=21.0.0; extra == "dev"
Requires-Dist: flake8>=3.8.0; extra == "dev"
Requires-Dist: mypy>=0.800; extra == "dev"
Dynamic: author
Dynamic: classifier
Dynamic: description
Dynamic: description-content-type
Dynamic: home-page
Dynamic: keywords
Dynamic: project-url
Dynamic: provides-extra
Dynamic: requires-dist
Dynamic: requires-python
Dynamic: summary
